pubmed_citations/__init__.py
pubmed_citations/bin.py
pubmed_citations/core.py
pubmed_citations/version.json
pubmed_citations/utils/__init__.py
pubmed_citations/utils/export_csv.py
pubmed_citations/utils/export_docx.py
pubmed_citations/utils/export_excel.py
pubmed_citations/utils/export_json.py
pubmed_citations/utils/get_pmid_list.py
pubmed_citations-1.0.0.dist-info/METADATA
pubmed_citations-1.0.0.dist-info/WHEEL
pubmed_citations-1.0.0.dist-info/entry_points.txt
pubmed_citations-1.0.0.dist-info/top_level.txt
pubmed_citations-1.0.0.dist-info/RECORD
