Metadata-Version: 2.1
Name: pubmed-citations
Version: 1.0.0
Summary: Generate citations for PubMed articles
Home-page: https://github.com/suqingdong/pubmed_citations
Author: suqingdong
Author-email: suqingdong1114@gmail.com
License: MIT License
Platform: UNKNOWN
Classifier: Development Status :: 5 - Production/Stable
Classifier: Operating System :: OS Independent
Classifier: Intended Audience :: Developers
Classifier: License :: OSI Approved :: MIT License
Classifier: Programming Language :: Python
Classifier: Programming Language :: Python :: 3
Classifier: Programming Language :: Python :: 3.8
Classifier: Programming Language :: Python :: 3.9
Classifier: Programming Language :: Python :: 3.10
Classifier: Programming Language :: Python :: 3.11
Classifier: Topic :: Software Development :: Libraries
Requires-Dist: click
Requires-Dist: loguru
Requires-Dist: openpyxl
Requires-Dist: python-docx
Requires-Dist: webrequests
